eras/__init__.py
eras/main.py
eras/run.ipynb
eras/__pycache__/__init__.cpython-311.pyc
eras/__pycache__/__init__.cpython-39.pyc
eras/__pycache__/main.cpython-311.pyc
eras/agents/__init__.py
eras/agents/llama_functions_agent.py
eras/agents/llama_terminal_command_functions_agent.py
eras/agents/llm_functions_agent.py
eras/agents/simple_llm.py
eras/agents/terminal_llama_agent.py
eras/agents/__pycache__/__init__.cpython-311.pyc
eras/agents/__pycache__/llama_functions_agent.cpython-311.pyc
eras/agents/__pycache__/llama_terminal_command_functions_agent.cpython-311.pyc
eras/agents/__pycache__/llm_functions_agent.cpython-311.pyc
eras/agents/__pycache__/llm_functions_agent.cpython-39.pyc
eras/agents/__pycache__/simple_llm.cpython-311.pyc
eras/agents/__pycache__/terminal_llama_agent.cpython-311.pyc
eras/agents/__pycache__/terminal_llama_agent.cpython-39.pyc
eras/config/__init__.py
eras/config/config.py
eras/config/__pycache__/__init__.cpython-311.pyc
eras/config/__pycache__/config.cpython-311.pyc
eras/config/__pycache__/config.cpython-39.pyc
eras/decorators/__init__.py
eras/decorators/chatgpt_tool_data.py
eras/decorators/__pycache__/chatgpt_tool_data.cpython-311.pyc
eras/decorators/__pycache__/chatgpt_tool_data.cpython-39.pyc
eras/factories/__init__.py
eras/factories/function_details_factory.py
eras/factories/message_factory.py
eras/factories/__pycache__/__init__.cpython-311.pyc
eras/factories/__pycache__/function_details_factory.cpython-311.pyc
eras/factories/__pycache__/function_details_factory.cpython-39.pyc
eras/factories/__pycache__/message_factory.cpython-311.pyc
eras/factories/__pycache__/message_factory.cpython-39.pyc
eras/models/__init__.py
eras/models/constants.py
eras/models/conversation.py
eras/models/function_details.py
eras/models/message.py
eras/models/simple_stream_inference_callable.py
eras/models/transaction.py
eras/models/__pycache__/__init__.cpython-311.pyc
eras/models/__pycache__/constants.cpython-311.pyc
eras-0.5.2.dist-info/LICENSE
eras-0.5.2.dist-info/METADATA
eras-0.5.2.dist-info/WHEEL
eras-0.5.2.dist-info/entry_points.txt
eras-0.5.2.dist-info/top_level.txt
eras-0.5.2.dist-info/RECORD
