Metadata-Version: 2.1
Name: eras
Version: 0.5.2
Summary: A terminal command library that provides a Natural Language Interface for running shell commands.
Home-page: https://github.com/jasonmcaffee/eras-project
Author: Jason McAffee
Author-email: jasonlmcaffee@gmail.com
Classifier: Programming Language :: Python :: 3
Classifier: License :: OSI Approved :: MIT License
Classifier: Operating System :: OS Independent
Requires-Python: >=3.6
License-File: LICENSE
Requires-Dist: openai ==1.26.0
Requires-Dist: keyboard ==0.13.5
Requires-Dist: python-dotenv ==1.0.0
Requires-Dist: asyncio ==3.4.3
Requires-Dist: InquirerPy ==0.3.4
Requires-Dist: colorama ==0.4.6
Requires-Dist: requests ==2.31.0
Requires-Dist: ga4mp ==2.0.4
